everyrow/__init__.py
everyrow/api_utils.py
everyrow/citations.py
everyrow/constants.py
everyrow/ops.py
everyrow/result.py
everyrow/session.py
everyrow/task.py
everyrow/generated/__init__.py
everyrow/generated/client.py
everyrow/generated/errors.py
everyrow/generated/py.typed
everyrow/generated/types.py
everyrow/generated/api/__init__.py
everyrow/generated/api/default/__init__.py
everyrow/generated/api/default/continue_task_endpoint_tasks_continue_post.py
everyrow/generated/api/default/copy_artifacts_artifacts_copy_post.py
everyrow/generated/api/default/copy_workflow_endpoint_workflows_copy_post.py
everyrow/generated/api/default/create_api_key_endpoint_api_keys_create_post.py
everyrow/generated/api/default/create_session_endpoint_sessions_create_post.py
everyrow/generated/api/default/create_workflow_from_artifact_workflows_from_artifact_post.py
everyrow/generated/api/default/export_to_google_sheets_export_post.py
everyrow/generated/api/default/generate_feedback_endpoint_tasks_generate_feedback_post.py
everyrow/generated/api/default/get_artifacts_artifacts_get.py
everyrow/generated/api/default/get_default_timeout_seconds_models_default_timeout_seconds_get.py
everyrow/generated/api/default/get_job_progress_for_task_jobs_progress_get.py
everyrow/generated/api/default/get_metrics_metrics_get.py
everyrow/generated/api/default/get_queues_stats_jobs_queues_get.py
everyrow/generated/api/default/get_task_status_endpoint_tasks_task_id_status_get.py
everyrow/generated/api/default/get_user_usage_usage_get.py
everyrow/generated/api/default/healthz_healthz_get.py
everyrow/generated/api/default/import_from_google_sheets_import_post.py
everyrow/generated/api/default/interrupt_chat_task_tasks_chat_interrupt_post.py
everyrow/generated/api/default/list_api_keys_endpoint_api_keys_get.py
everyrow/generated/api/default/re_execute_task_endpoint_tasks_re_execute_post.py
everyrow/generated/api/default/revoke_api_key_endpoint_api_keys_key_id_revoke_post.py
everyrow-0.1.10.dist-info/METADATA
everyrow-0.1.10.dist-info/WHEEL
everyrow-0.1.10.dist-info/licenses/LICENSE.txt
everyrow-0.1.10.dist-info/RECORD
