Metadata-Version: 2.4
Name: everyrow
Version: 0.1.10
Summary: An SDK for everyrow.io: agent ops at spreadsheet scale
License-File: LICENSE.txt
Requires-Python: >=3.12
Requires-Dist: attrs>=22.2.0
Requires-Dist: httpx>=0.20.0
Requires-Dist: pandas>=2.0.0
Requires-Dist: pydantic<3.0.0,>=2.0.0
Requires-Dist: python-dateutil>=2.7.0
